Workbook

Sheet Dashboard
B1: DASHBOARD DE VENDAS · XBOX
B4: Ano: | C4: Todos | E4: Região: | F4: Todas | H4: Categoria: | I4: Todas | L4: ◄ Use as listas suspensas amarelas para filtrar
B6: RECEITA | D6: LUCRO | F6: MARGEM | H6: PEDIDOS | J6: UNIDADES | L6: TICKET MÉDIO
B7: =Calc!B6 -> 941005 | D7: =Calc!B7 -> 273760 | F7: =Calc!B11 -> 0.290923 | H7: =Calc!B9 -> 720 | J7: =Calc!B8 -> 1705 | L7: =Calc!B10 -> 1306.9514
B58: Fonte: aba 'Base' · Todos os números são fórmulas (SUMIFS) e respondem aos filtros acima. Dados de exemplo (simulados).

Sheet Base
A1: Data | B1: Pedido | C1: Produto | D1: Categoria | E1: Região | F1: Vendedor | G1: Quantidade | H1: Preço Unitário | I1: Custo Unitário | J1: Receita | K1: Custo Total | L1: Lucro | M1: Ano | N1: Mês
A2: 45292 | B2: PED-0001 | C2: Headset Gamer | D2: Acessórios | E2: Sudeste | F2: Diego Alves | G2: 4 | H2: 599 | I2: 380 | J2: =G2*H2 -> 2396 | K2: =G2*I2 -> 1520 | L2: =J2-K2 -> 876 | M2: =YEAR(A2)&"" -> 2024 | N2: =MONTH(A2) -> 1
A3: 45292 | B3: PED-0002 | C3: Headset Gamer | D3: Acessórios | E3: Sudeste | F3: Ana Souza | G3: 4 | H3: 599 | I3: 380 | J3: =G3*H3 -> 2396 | K3: =G3*I3 -> 1520 | L3: =J3-K3 -> 876 | M3: =YEAR(A3)&"" -> 2024 | N3: =MONTH(A3) -> 1
A4: 45293 | B4: PED-0003 | C4: Game Pass Ultimate 3m | D4: Assinaturas | E4: Norte | F4: Carla Dias | G4: 1 | H4: 149 | I4: 95 | J4: =G4*H4 -> 149 | K4: =G4*I4 -> 95 | L4: =J4-K4 -> 54 | M4: =YEAR(A4)&"" -> 2024 | N4: =MONTH(A4) -> 1
A5: 45294 | B5: PED-0004 | C5: Controle Wireless | D5: Acessórios | E5: Nordeste | F5: Felipe Costa | G5: 1 | H5: 399 | I5: 250 | J5: =G5*H5 -> 399 | K5: =G5*I5 -> 250 | L5: =J5-K5 -> 149 | M5: =YEAR(A5)&"" -> 2024 | N5: =MONTH(A5) -> 1
A6: 45295 | B6: PED-0005 | C6: Xbox Series X | D6: Consoles | E6: Norte | F6: Bruno Lima | G6: 1 | H6: 4499 | I6: 3600 | J6: =G6*H6 -> 4499 | K6: =G6*I6 -> 3600 | L6: =J6-K6 -> 899 | M6: =YEAR(A6)&"" -> 2024 | N6: =MONTH(A6) -> 1
A7: 45295 | B7: PED-0006 | C7: Starfield | D7: Jogos | E7: Sudeste | F7: Diego Alves | G7: 2 | H7: 299 | I7: 180 | J7: =G7*H7 -> 598 | K7: =G7*I7 -> 360 | L7: =J7-K7 -> 238 | M7: =YEAR(A7)&"" -> 2024 | N7: =MONTH(A7) -> 1
A8: 45297 | B8: PED-0007 | C8: Halo Infinite | D8: Jogos | E8: Sul | F8: Carla Dias | G8: 2 | H8: 249 | I8: 150 | J8: =G8*H8 -> 498 | K8: =G8*I8 -> 300 | L8: =J8-K8 -> 198 | M8: =YEAR(A8)&"" -> 2024 | N8: =MONTH(A8) -> 1
A9: 45298 | B9: PED-0008 | C9: Forza Horizon 5 | D9: Jogos | E9: Nordeste | F9: Felipe Costa | G9: 2 | H9: 249 | I9: 150 | J9: =G9*H9 -> 498 | K9: =G9*I9 -> 300 | L9: =J9-K9 -> 198 | M9: =YEAR(A9)&"" -> 2024 | N9: =MONTH(A9) -> 1
A10: 45298 | B10: PED-0009 | C10: Forza Horizon 5 | D10: Jogos | E10: Norte | F10: Ana Souza | G10: 2 | H10: 249 | I10: 150 | J10: =G10*H10 -> 498 | K10: =G10*I10 -> 300 | L10: =J10-K10 -> 198 | M10: =YEAR(A10)&"" -> 2024 | N10: =MONTH(A10) -> 1
A11: 45299 | B11: PED-0010 | C11: Halo Infinite | D11: Jogos | E11: Sul | F11: Diego Alves | G11: 3 | H11: 249 | I11: 150 | J11: =G11*H11 -> 747 | K11: =G11*I11 -> 450 | L11: =J11-K11 -> 297 | M11: =YEAR(A11)&"" -> 2024 | N11: =MONTH(A11) -> 1
A12: 45300 | B12: PED-0011 | C12: Game Pass Ultimate 3m | D12: Assinaturas | E12: Sudeste | F12: Felipe Costa | G12: 2 | H12: 149 | I12: 95 | J12: =G12*H12 -> 298 | K12: =G12*I12 -> 190 | L12: =J12-K12 -> 108 | M12: =YEAR(A12)&"" -> 2024 | N12: =MONTH(A12) -> 1
A13: 45301 | B13: PED-0012 | C13: Starfield | D13: Jogos | E13: Sudeste | F13: Carla Dias | G13: 2 | H13: 299 | I13: 180 | J13: =G13*H13 -> 598 | K13: =G13*I13 -> 360 | L13: =J13-K13 -> 238 | M13: =YEAR(A13)&"" -> 2024 | N13: =MONTH(A13) -> 1
... A721: 46017 | B721: PED-0720 | C721: Game Pass Ultimate 3m | D721: Assinaturas | E721: Sudeste | F721: Carla Dias | G721: 4 | H721: 149 | I721: 95 | J721: =G721*H721 -> 596 | K721: =G721*I721 -> 380 | L721: =J721-K721 -> 216 | M721: =YEAR(A721)&"" -> 2025 | N721: =MONTH(A721) -> 12

Sheet Calc
A1: Filtros aplicados (vêm do Dashboard)
A2: Ano | B2: =IF(Dashboard!C4="Todos","*",Dashboard!C4) -> *
A3: Região | B3: =IF(Dashboard!F4="Todas","*",Dashboard!F4) -> *
A4: Categoria | B4: =IF(Dashboard!I4="Todas","*",Dashboard!I4) -> *
A5: KPIs
A6: Receita | B6: =SUMIFS(Base!$J$2:$J$721,Base!$M$2:$M$721,$B$2,Base!$E$2:$E$721,$B$3,Base!$D$2:$D$721,$B$4) -> 941005
A7: Lucro | B7: =SUMIFS(Base!$L$2:$L$721,Base!$M$2:$M$721,$B$2,Base!$E$2:$E$721,$B$3,Base!$D$2:$D$721,$B$4) -> 273760
A8: Unidades | B8: =SUMIFS(Base!$G$2:$G$721,Base!$M$2:$M$721,$B$2,Base!$E$2:$E$721,$B$3,Base!$D$2:$D$721,$B$4) -> 1705
A9: Pedidos | B9: =COUNTIFS(Base!$M$2:$M$721,$B$2,Base!$E$2:$E$721,$B$3,Base!$D$2:$D$721,$B$4) -> 720
A10: Ticket Médio | B10: =IF(B9=0,0,B6/B9) -> 1306.9514
A11: Margem | B11: =IF(B6=0,0,B7/B6) -> 0.290923
A14: Mês | B14: Receita | C14: Lucro | E14: Categoria | F14: Receita | H14: Região | I14: Receita | K14: Produto | L14: Receita | M14: Aux (desempate) | O14: Top 5 Produto | P14: Receita | R14: Vendedor | S14: Receita
A15: Jan | B15: =SUMIFS(Base!$J$2:$J$721,Base!$M$2:$M$721,$B$2,Base!$E$2:$E$721,$B$3,Base!$D$2:$D$721,$B$4,Base!$N$2:$N$721,1) -> 53535 | C15: =SUMIFS(Base!$L$2:$L$721,Base!$M$2:$M$721,$B$2,Base!$E$2:$E$721,$B$3,Base!$D$2:$D$721,$B$4,Base!$N$2:$N$721,1) -> 18490 | E15: Consoles | F15: =SUMIFS(Base!$J$2:$J$721,Base!$M$2:$M$721,$B$2,Base!$E$2:$E$721,$B$3,Base!$D$2:$D$721,E15) -> 441864 | H15: Sudeste | I15: =SUMIFS(Base!$J$2:$J$721,Base!$M$2:$M$721,$B$2,Base!$D$2:$D$721,$B$4,Base!$E$2:$E$721,H15) -> 335360 | K15: Xbox Series X | L15: =SUMIFS(Base!$J$2:$J$721,Base!$M$2:$M$721,$B$2,Base!$E$2:$E$721,$B$3,Base!$D$2:$D$721,$B$4,Base!$C$2:$C$721,K15) -> 229449 | M15: =L15+ROW()/1000000 -> 229449 | O15: =INDEX($K$15:$K$26,MATCH(LARGE($M$15:$M$26,1),$M$15:$M$26,0)) -> Xbox Series X | P15: =INDEX($L$15:$L$26,MATCH(LARGE($M$15:$M$26,1),$M$15:$M$26,0)) -> 229449 | R15: Ana Souza | S15: =SUMIFS(Base!$J$2:$J$721,Base!$M$2:$M$721,$B$2,Base!$E$2:$E$721,$B$3,Base!$D$2:$D$721,$B$4,Base!$F$2:$F$721,R15) -> 127558
A16: Fev | B16: =SUMIFS(Base!$J$2:$J$721,Base!$M$2:$M$721,$B$2,Base!$E$2:$E$721,$B$3,Base!$D$2:$D$721,$B$4,Base!$N$2:$N$721,2) -> 54904 | C16: =SUMIFS(Base!$L$2:$L$721,Base!$M$2:$M$721,$B$2,Base!$E$2:$E$721,$B$3,Base!$D$2:$D$721,$B$4,Base!$N$2:$N$721,2) -> 17219 | E16: Acessórios | F16: =SUMIFS(Base!$J$2:$J$721,Base!$M$2:$M$721,$B$2,Base!$E$2:$E$721,$B$3,Base!$D$2:$D$721,E16) -> 257958 | H16: Sul | I16: =SUMIFS(Base!$J$2:$J$721,Base!$M$2:$M$721,$B$2,Base!$D$2:$D$721,$B$4,Base!$E$2:$E$721,H16) -> 194893 | K16: Xbox Series S | L16: =SUMIFS(Base!$J$2:$J$721,Base!$M$2:$M$721,$B$2,Base!$E$2:$E$721,$B$3,Base!$D$2:$D$721,$B$4,Base!$C$2:$C$721,K16) -> 212415 | M16: =L16+ROW()/1000000 -> 212415 | O16: =INDEX($K$15:$K$26,MATCH(LARGE($M$15:$M$26,2),$M$15:$M$26,0)) -> Xbox Series S | P16: =INDEX($L$15:$L$26,MATCH(LARGE($M$15:$M$26,2),$M$15:$M$26,0)) -> 212415 | R16: Bruno Lima | S16: =SUMIFS(Base!$J$2:$J$721,Base!$M$2:$M$721,$B$2,Base!$E$2:$E$721,$B$3,Base!$D$2:$D$721,$B$4,Base!$F$2:$F$721,R16) -> 149183
A17: Mar | B17: =SUMIFS(Base!$J$2:$J$721,Base!$M$2:$M$721,$B$2,Base!$E$2:$E$721,$B$3,Base!$D$2:$D$721,$B$4,Base!$N$2:$N$721,3) -> 86976 | C17: =SUMIFS(Base!$L$2:$L$721,Base!$M$2:$M$721,$B$2,Base!$E$2:$E$721,$B$3,Base!$D$2:$D$721,$B$4,Base!$N$2:$N$721,3) -> 25146 | E17: Jogos | F17: =SUMIFS(Base!$J$2:$J$721,Base!$M$2:$M$721,$B$2,Base!$E$2:$E$721,$B$3,Base!$D$2:$D$721,E17) -> 161250 | H17: Nordeste | I17: =SUMIFS(Base!$J$2:$J$721,Base!$M$2:$M$721,$B$2,Base!$D$2:$D$721,$B$4,Base!$E$2:$E$721,H17) -> 179295 | K17: Controle Wireless | L17: =SUMIFS(Base!$J$2:$J$721,Base!$M$2:$M$721,$B$2,Base!$E$2:$E$721,$B$3,Base!$D$2:$D$721,$B$4,Base!$C$2:$C$721,K17) -> 86184 | M17: =L17+ROW()/1000000 -> 86184 | O17: =INDEX($K$15:$K$26,MATCH(LARGE($M$15:$M$26,3),$M$15:$M$26,0)) -> Headset Gamer | P17: =INDEX($L$15:$L$26,MATCH(LARGE($M$15:$M$26,3),$M$15:$M$26,0)) -> 104226 | R17: Carla Dias | S17: =SUMIFS(Base!$J$2:$J$721,Base!$M$2:$M$721,$B$2,Base!$E$2:$E$721,$B$3,Base!$D$2:$D$721,$B$4,Base!$F$2:$F$721,R17) -> 138528
A18: Abr | B18: =SUMIFS(Base!$J$2:$J$721,Base!$M$2:$M$721,$B$2,Base!$E$2:$E$721,$B$3,Base!$D$2:$D$721,$B$4,Base!$N$2:$N$721,4) -> 84467 | C18: =SUMIFS(Base!$L$2:$L$721,Base!$M$2:$M$721,$B$2,Base!$E$2:$E$721,$B$3,Base!$D$2:$D$721,$B$4,Base!$N$2:$N$721,4) -> 25177 | E18: Assinaturas | F18: =SUMIFS(Base!$J$2:$J$721,Base!$M$2:$M$721,$B$2,Base!$E$2:$E$721,$B$3,Base!$D$2:$D$721,E18) -> 79933 | H18: Centro-Oeste | I18: =SUMIFS(Base!$J$2:$J$721,Base!$M$2:$M$721,$B$2,Base!$D$2:$D$721,$B$4,Base!$E$2:$E$721,H18) -> 98462 | K18: Headset Gamer | L18: =SUMIFS(Base!$J$2:$J$721,Base!$M$2:$M$721,$B$2,Base!$E$2:$E$721,$B$3,Base!$D$2:$D$721,$B$4,Base!$C$2:$C$721,K18) -> 104226 | M18: =L18+ROW()/1000000 -> 104226 | O18: =INDEX($K$15:$K$26,MATCH(LARGE($M$15:$M$26,4),$M$15:$M$26,0)) -> Controle Wireless | P18: =INDEX($L$15:$L$26,MATCH(LARGE($M$15:$M$26,4),$M$15:$M$26,0)) -> 86184 | R18: Diego Alves | S18: =SUMIFS(Base!$J$2:$J$721,Base!$M$2:$M$721,$B$2,Base!$E$2:$E$721,$B$3,Base!$D$2:$D$721,$B$4,Base!$F$2:$F$721,R18) -> 166186
A19: Mai | B19: =SUMIFS(Base!$J$2:$J$721,Base!$M$2:$M$721,$B$2,Base!$E$2:$E$721,$B$3,Base!$D$2:$D$721,$B$4,Base!$N$2:$N$721,5) -> 74480 | C19: =SUMIFS(Base!$L$2:$L$721,Base!$M$2:$M$721,$B$2,Base!$E$2:$E$721,$B$3,Base!$D$2:$D$721,$B$4,Base!$N$2:$N$721,5) -> 21065 | H19: Norte | I19: =SUMIFS(Base!$J$2:$J$721,Base!$M$2:$M$721,$B$2,Base!$D$2:$D$721,$B$4,Base!$E$2:$E$721,H19) -> 132995 | K19: Cartão de Armazenamento 1TB | L19: =SUMIFS(Base!$J$2:$J$721,Base!$M$2:$M$721,$B$2,Base!$E$2:$E$721,$B$3,Base!$D$2:$D$721,$B$4,Base!$C$2:$C$721,K19) -> 67548 | M19: =L19+ROW()/1000000 -> 67548 | O19: =INDEX($K$15:$K$26,MATCH(LARGE($M$15:$M$26,5),$M$15:$M$26,0)) -> Cartão de Armazenamento 1TB | P19: =INDEX($L$15:$L$26,MATCH(LARGE($M$15:$M$26,5),$M$15:$M$26,0)) -> 67548 | R19: Elisa Prado | S19: =SUMIFS(Base!$J$2:$J$721,Base!$M$2:$M$721,$B$2,Base!$E$2:$E$721,$B$3,Base!$D$2:$D$721,$B$4,Base!$F$2:$F$721,R19) -> 202108
A20: Jun | B20: =SUMIFS(Base!$J$2:$J$721,Base!$M$2:$M$721,$B$2,Base!$E$2:$E$721,$B$3,Base!$D$2:$D$721,$B$4,Base!$N$2:$N$721,6) -> 105663 | C20: =SUMIFS(Base!$L$2:$L$721,Base!$M$2:$M$721,$B$2,Base!$E$2:$E$721,$B$3,Base!$D$2:$D$721,$B$4,Base!$N$2:$N$721,6) -> 28088 | K20: Game Pass Ultimate 3m | L20: =SUMIFS(Base!$J$2:$J$721,Base!$M$2:$M$721,$B$2,Base!$E$2:$E$721,$B$3,Base!$D$2:$D$721,$B$4,Base!$C$2:$C$721,K20) -> 36505 | M20: =L20+ROW()/1000000 -> 36505 | R20: Felipe Costa | S20: =SUMIFS(Base!$J$2:$J$721,Base!$M$2:$M$721,$B$2,Base!$E$2:$E$721,$B$3,Base!$D$2:$D$721,$B$4,Base!$F$2:$F$721,R20) -> 157442
A21: Jul | B21: =SUMIFS(Base!$J$2:$J$721,Base!$M$2:$M$721,$B$2,Base!$E$2:$E$721,$B$3,Base!$D$2:$D$721,$B$4,Base!$N$2:$N$721,7) -> 104396 | C21: =SUMIFS(Base!$L$2:$L$721,Base!$M$2:$M$721,$B$2,Base!$E$2:$E$721,$B$3,Base!$D$2:$D$721,$B$4,Base!$N$2:$N$721,7) -> 28581 | K21: Game Pass Core 12m | L21: =SUMIFS(Base!$J$2:$J$721,Base!$M$2:$M$721,$B$2,Base!$E$2:$E$721,$B$3,Base!$D$2:$D$721,$B$4,Base!$C$2:$C$721,K21) -> 43428 | M21: =L21+ROW()/1000000 -> 43428
A22: Ago | B22: =SUMIFS(Base!$J$2:$J$721,Base!$M$2:$M$721,$B$2,Base!$E$2:$E$721,$B$3,Base!$D$2:$D$721,$B$4,Base!$N$2:$N$721,8) -> 90146 | C22: =SUMIFS(Base!$L$2:$L$721,Base!$M$2:$M$721,$B$2,Base!$E$2:$E$721,$B$3,Base!$D$2:$D$721,$B$4,Base!$N$2:$N$721,8) -> 25781 | K22: Halo Infinite | L22: =SUMIFS(Base!$J$2:$J$721,Base!$M$2:$M$721,$B$2,Base!$E$2:$E$721,$B$3,Base!$D$2:$D$721,$B$4,Base!$C$2:$C$721,K22) -> 49302 | M22: =L22+ROW()/1000000 -> 49302
A23: Set | B23: =SUMIFS(Base!$J$2:$J$721,Base!$M$2:$M$721,$B$2,Base!$E$2:$E$721,$B$3,Base!$D$2:$D$721,$B$4,Base!$N$2:$N$721,9) -> 101350 | C23: =SUMIFS(Base!$L$2:$L$721,Base!$M$2:$M$721,$B$2,Base!$E$2:$E$721,$B$3,Base!$D$2:$D$721,$B$4,Base!$N$2:$N$721,9) -> 27265 | K23: Forza Horizon 5 | L23: =SUMIFS(Base!$J$2:$J$721,Base!$M$2:$M$721,$B$2,Base!$E$2:$E$721,$B$3,Base!$D$2:$D$721,$B$4,Base!$C$2:$C$721,K23) -> 43077 | M23: =L23+ROW()/1000000 -> 43077
A24: Out | B24: =SUMIFS(Base!$J$2:$J$721,Base!$M$2:$M$721,$B$2,Base!$E$2:$E$721,$B$3,Base!$D$2:$D$721,$B$4,Base!$N$2:$N$721,10) -> 71674 | C24: =SUMIFS(Base!$L$2:$L$721,Base!$M$2:$M$721,$B$2,Base!$E$2:$E$721,$B$3,Base!$D$2:$D$721,$B$4,Base!$N$2:$N$721,10) -> 20184 | K24: Starfield | L24: =SUMIFS(Base!$J$2:$J$721,Base!$M$2:$M$721,$B$2,Base!$E$2:$E$721,$B$3,Base!$D$2:$D$721,$B$4,Base!$C$2:$C$721,K24) -> 39767 | M24: =L24+ROW()/1000000 -> 39767
A25: Nov | B25: =SUMIFS(Base!$J$2:$J$721,Base!$M$2:$M$721,$B$2,Base!$E$2:$E$721,$B$3,Base!$D$2:$D$721,$B$4,Base!$N$2:$N$721,11) -> 71634 | C25: =SUMIFS(Base!$L$2:$L$721,Base!$M$2:$M$721,$B$2,Base!$E$2:$E$721,$B$3,Base!$D$2:$D$721,$B$4,Base!$N$2:$N$721,11) -> 22609 | K25: Gears 5 | L25: =SUMIFS(Base!$J$2:$J$721,Base!$M$2:$M$721,$B$2,Base!$E$2:$E$721,$B$3,Base!$D$2:$D$721,$B$4,Base!$C$2:$C$721,K25) -> 14155 | M25: =L25+ROW()/1000000 -> 14155
A26: Dez | B26: =SUMIFS(Base!$J$2:$J$721,Base!$M$2:$M$721,$B$2,Base!$E$2:$E$721,$B$3,Base!$D$2:$D$721,$B$4,Base!$N$2:$N$721,12) -> 41780 | C26: =SUMIFS(Base!$L$2:$L$721,Base!$M$2:$M$721,$B$2,Base!$E$2:$E$721,$B$3,Base!$D$2:$D$721,$B$4,Base!$N$2:$N$721,12) -> 14155 | K26: Minecraft | L26: =SUMIFS(Base!$J$2:$J$721,Base!$M$2:$M$721,$B$2,Base!$E$2:$E$721,$B$3,Base!$D$2:$D$721,$B$4,Base!$C$2:$C$721,K26) -> 14949 | M26: =L26+ROW()/1000000 -> 14949
